openbb_qa/__init__.py
openbb_qa/py.typed
openbb_qa/qa_helpers.py
openbb_qa/qa_models.py
openbb_qa/qa_router.py
openbb_qa-0.1.0a5.dist-info/METADATA
openbb_qa-0.1.0a5.dist-info/WHEEL
openbb_qa-0.1.0a5.dist-info/entry_points.txt
openbb_qa-0.1.0a5.dist-info/RECORD
