Metadata-Version: 2.1
Name: openbb-qa
Version: 0.1.0a5
Summary: Quantitative Analysis extension for OpenBB
Author: OpenBB Team
Author-email: hello@openbb.co
Requires-Python: >=3.8,<3.12
Classifier: Programming Language :: Python :: 3
Classifier: Programming Language :: Python :: 3.8
Classifier: Programming Language :: Python :: 3.9
Classifier: Programming Language :: Python :: 3.10
Classifier: Programming Language :: Python :: 3.11
Requires-Dist: openbb-core (>=0.1.0a5,<0.2.0)
Requires-Dist: pandas-ta (>=0.3.14b,<0.4.0)
Requires-Dist: scipy (>=1.10.1,<2.0.0)
Requires-Dist: statsmodels (>=0.14.0,<0.15.0)
